averell/__init__.py
averell/__main__.py
averell/cli.py
averell/core.py
averell/corpora.yaml
averell/utils.py
averell/readers/__init__.py
averell/readers/bibliotecaitaliana.py
averell/readers/czechverse.py
averell/readers/disco.py
averell/readers/disco3.py
averell/readers/ecpa.py
averell/readers/forbetter4verse.py
averell/readers/gongocorpus.py
averell/readers/metriqueenligne.py
averell/readers/plsdo.py
averell/readers/sdo.py
averell/readers/stichotheque.py
averell-1.2.2.dist-info/AUTHORS.rst
averell-1.2.2.dist-info/LICENSE
averell-1.2.2.dist-info/METADATA
averell-1.2.2.dist-info/WHEEL
averell-1.2.2.dist-info/entry_points.txt
averell-1.2.2.dist-info/top_level.txt
averell-1.2.2.dist-info/RECORD
